subzero/__init__.py
subzero/dist.py
subzero/rtf.py
subzero/utils.py
subzero/windist.py
subzero-0.2.4.dist-info/DESCRIPTION.rst
subzero-0.2.4.dist-info/METADATA
subzero-0.2.4.dist-info/RECORD
subzero-0.2.4.dist-info/WHEEL
subzero-0.2.4.dist-info/metadata.json
subzero-0.2.4.dist-info/top_level.txt
