Metadata-Version: 2.0
Name: subzero
Version: 0.2.4
Summary: PyInstaller setuptools integration
Home-page: https://github.com/xoviat/subzero
Author: Mars Galactic
Author-email: xoviat@users.noreply.github.com
License: GNU GENERAL PUBLIC LICENSE
Keywords: pyinstaller
Platform: any
Requires-Dist: PyInstaller
Requires-Dist: PyRTF3 (>=0.47.3)
Requires-Dist: deepmerge
Requires-Dist: packaging
Requires-Dist: pipdeptree
Requires-Dist: pyspin
Requires-Dist: contextlib2; python_version < "3.4"
Requires-Dist: pathlib; python_version < "3.4"
Requires-Dist: glob2; python_version < "3.5"
Requires-Dist: pywix (>=0.2); sys_platform == "win32"
